setup.py
jsonipy/__init__.py
jsonipy/serializers.py
jsonipy.egg-info/PKG-INFO
jsonipy.egg-info/SOURCES.txt
jsonipy.egg-info/dependency_links.txt
jsonipy.egg-info/top_level.txt
tests/__init__.py
tests/tests.py