Metadata-Version: 1.0
Name: jsonipy
Version: 0.1
Summary: converts your objects into JSON 
Home-page: http://github.com/rahulrd/jsonipy
Author: Rahul Dwivedi
Author-email: rahulrd005@gmail.com
License: MIT
Keywords: JSON object convert serialize
Platform: UNKNOWN
